src/design/module_7_segments.v
module module_7_segments # (

    parameter DISPLAY_REFRESH = 27000
)(

    input clk_i,
    input rst_i,

    input [7 : 0] bcd_i,

    output reg [1 : 0] anodo_o,
    output reg [6 : 0] catodo_o
);

    localparam WIDTH_DISPLAY_COUNTER = $clog2(DISPLAY_REFRESH);
    reg [WIDTH_DISPLAY_COUNTER - 1 : 0] cuenta_salida;

    reg [3 : 0] digito_o;

    reg en_conmutador;
    reg [1 : 0]decena_unidad;

    // Contador de refresco
    always @ (posedge clk_i or negedge rst_i) begin
        if (!rst_i) begin
            cuenta_salida <= DISPLAY_REFRESH - 1;
            en_conmutador <= 0;
        end else begin
            cuenta_salida <= (cuenta_salida == 0) ? (DISPLAY_REFRESH - 1) : (cuenta_salida - 1'b1);
            en_conmutador <= (cuenta_salida == 0);
        end
    end

    // Contador de 1 bit 
    always @ (posedge clk_i) begin
        decena_unidad <= (rst_i) ? ((en_conmutador) ? (decena_unidad + 1'b1) : decena_unidad) : 2'b00;
    end

     //Multiplexed digits
    always @(decena_unidad) begin

        digito_o = 0;
        anodo_o = 2'b11;
        
        case(decena_unidad) 
            
            1'b0 : begin
                
                anodo_o  = 2'b10;
                digito_o = bcd_i [3 : 0];
            end

            1'b1 : begin
                
                anodo_o  = 2'b01;
                digito_o = bcd_i [7 : 4]; 
            end

            default: begin
                
                anodo_o  = 2'b11;
                digito_o = 0;
            end
        endcase
    end

    //BCD to 7 segments
    always @(*) begin
        catodo_o[0] = ~(digito_o == 4'd0 || digito_o == 4'd2 || digito_o == 4'd3 || digito_o == 4'd5 || digito_o == 4'd6 || digito_o == 4'd7 || digito_o == 4'd8 || digito_o == 4'd9);
        catodo_o[1] = ~(digito_o == 4'd0 || digito_o == 4'd1 || digito_o == 4'd2 || digito_o == 4'd3 || digito_o == 4'd4 || digito_o == 4'd7 || digito_o == 4'd8 || digito_o == 4'd9);
        catodo_o[2] = ~(digito_o == 4'd0 || digito_o == 4'd1 || digito_o == 4'd3 || digito_o == 4'd4 || digito_o == 4'd5 || digito_o == 4'd6 || digito_o == 4'd7 || digito_o == 4'd8 || digito_o == 4'd9);
        catodo_o[3] = ~(digito_o == 4'd0 || digito_o == 4'd2 || digito_o == 4'd3 || digito_o == 4'd5 || digito_o == 4'd6 || digito_o == 4'd8 || digito_o == 4'd9);
        catodo_o[4] = ~(digito_o == 4'd0 || digito_o == 4'd2 || digito_o == 4'd6 || digito_o == 4'd8);
        catodo_o[5] = ~(digito_o == 4'd0 || digito_o == 4'd4 || digito_o == 4'd5 || digito_o == 4'd6 || digito_o == 4'd8 || digito_o == 4'd9);
        catodo_o[6] = ~(digito_o == 4'd2 || digito_o == 4'd3 || digito_o == 4'd4 || digito_o == 4'd5 || digito_o == 4'd6 || digito_o == 4'd8 || digito_o == 4'd9);

    end
endmodule

src/design/module_bin_to_bcd.v
module module_bin_to_bcd #(
    parameter WIDTH = 4
)(
    input clk_i,
    input rst_i,
    input [WIDTH - 1 : 0] bin_i,
    output reg [7 : 0] bcd_o
);

    // Señales internas para las decenas y las unidades
    reg [3:0] unidades;
    reg [3:0] decenas;

    // Registros para sincronizar las señales internas
    reg [3:0] unidades_sync;
    reg [3:0] decenas_sync;

    // Lógica combinacional para calcular unidades y decenas
    always @(*) begin
        // Inicialización de las señales internas
        unidades = 4'b0000;
        decenas  = 4'b0000;

        // Determinar unidades y decenas basadas en el valor de bin_i
        case (bin_i)
            4'b0000: begin // 0
                unidades = 4'b0000;
                decenas  = 4'b0000;
            end
            4'b0001: begin // 1
                unidades = 4'b0001;
                decenas  = 4'b0000;
            end
            4'b0010: begin // 2
                unidades = 4'b0010;
                decenas  = 4'b0000;
            end
            4'b0011: begin // 3
                unidades = 4'b0011;
                decenas  = 4'b0000;
            end
            4'b0100: begin // 4
                unidades = 4'b0100;
                decenas  = 4'b0000;
            end
            4'b0101: begin // 5
                unidades = 4'b0101;
                decenas  = 4'b0000;
            end
            4'b0110: begin // 6
                unidades = 4'b0110;
                decenas  = 4'b0000;
            end
            4'b0111: begin // 7
                unidades = 4'b0111;
                decenas  = 4'b0000;
            end
            4'b1000: begin // 8
                unidades = 4'b1000;
                decenas  = 4'b0000;
            end
            4'b1001: begin // 9
                unidades = 4'b1001;
                decenas  = 4'b0000;
            end
            4'b1010: begin // 10
                unidades = 4'b0000;
                decenas  = 4'b0001;
            end
            4'b1011: begin // 11
                unidades = 4'b0001;
                decenas  = 4'b0001;
            end
            4'b1100: begin // 12
                unidades = 4'b0010;
                decenas  = 4'b0001;
            end
            4'b1101: begin // 13
                unidades = 4'b0011;
                decenas  = 4'b0001;
            end
            4'b1110: begin // 14
                unidades = 4'b0100;
                decenas  = 4'b0001;
            end
            4'b1111: begin // 15
                unidades = 4'b0101;
                decenas  = 4'b0001;
            end
            default: begin // Caso por defecto para valores no esperados
                unidades = 4'b0000;
                decenas  = 4'b0000;
            end
        endcase
    end

    // Sincronización de las señales internas con el reloj
    always @(posedge clk_i or negedge rst_i) begin
        if (~rst_i) begin
            unidades_sync <= 4'b0000;
            decenas_sync  <= 4'b0000;
        end else begin
            unidades_sync <= unidades;
            decenas_sync  <= decenas;
        end
    end

    // Lógica de salida con flip-flop para sincronización
    always @(posedge clk_i or negedge rst_i) 
    begin
        if (~rst_i) begin
            bcd_o <= 8'b0; // Resetear la salida a 0
        end else begin
            bcd_o[3:0] <= unidades_sync;  // Asignar el valor sincronizado de unidades a los 4 bits menos significativos
            bcd_o[7:4] <= decenas_sync;   // Asignar el valor sincronizado de decenas a los 4 bits más significativos
        end
    end
endmodule

src/design/module_input_deco_gray.v
module module_input_deco_gray # (
    parameter WIDTH = 4,                // Ancho del código Gray y del código binario
    parameter INPUT_REFRESH = 2700000   // Frecuencia de actualización para el contador
)(
    input                  clk_i,        // Señal de reloj
    input                  rst_i,        // Señal de reinicio asíncrono
    input [WIDTH - 1 : 0]  codigo_gray_i, // Entrada de código Gray

    output reg [WIDTH - 1 : 0] codigo_bin_o // Salida de código binario
);

    // Parámetros
    localparam WIDTH_INPUT_COUNTER = $clog2(INPUT_REFRESH); // Tamaño del contador de entrada

    // Señales internas
    reg [WIDTH - 1 : 0]               codigo_gray_sync_r; // Registro para almacenar el código Gray sincronizado
    reg [WIDTH_INPUT_COUNTER - 1 : 0] cuenta_entrada;    // Contador para la actualización de la entrada

    reg en_lectura; // Señal de habilitación de lectura

    // Contador de actualización
    always @(posedge clk_i) begin
        cuenta_entrada <= rst_i ? (cuenta_entrada == 0 ? (INPUT_REFRESH - 1) : (cuenta_entrada - 1)) : (INPUT_REFRESH - 1);
        en_lectura <= (cuenta_entrada == 0) && rst_i;
    end

    // Sincronización de entrada
    always @(posedge clk_i) begin
        codigo_gray_sync_r <= rst_i ? (en_lectura ? codigo_gray_i : codigo_gray_sync_r) : 0;
    end

    // Conversión de Gray a binario usando lógica booleana
    always_comb begin
        // Cálculo del código binario a partir del código Gray
        logic bit_a, bit_b, bit_c, bit_d;
        bit_a = codigo_gray_sync_r[3];
        bit_b = codigo_gray_sync_r[2];
        bit_c = codigo_gray_sync_r[1];
        bit_d = codigo_gray_sync_r[0];

        // Aplicar las fórmulas para convertir Gray a binario
        codigo_bin_o[3] = bit_a; // MSB del binario es igual al MSB del Gray
        codigo_bin_o[2] = (bit_a & ~bit_b) | (~bit_a & bit_b); // Segunda posición del binario
        codigo_bin_o[1] = codigo_bin_o[2] ^ bit_c; // Tercera posición del binario
        codigo_bin_o[0] = codigo_bin_o[1] ^ bit_d; // LSB del binario
    end

endmodule

src/design/module_top_deco_gray.v
module module_top_deco_gray # (
     parameter INPUT_REFRESH = 2700000,
     parameter DISPLAY_REFRESH = 27000
)(
    input                  clk_pi,
    input                  rst_pi,
    input [3 : 0]          codigo_gray_pi,

    output  [1 : 0]     anodo_po,
    output  [6 : 0]     catodo_po,              
    output  [3 : 0]     codigo_bin_led_po
);
    wire [3 : 0] codigo_bin;
    wire [7 : 0] codigo_bcd;

    generate
        module_input_deco_gray # (4, INPUT_REFRESH) SUBMODULE_INPUT (
            .clk_i         (clk_pi),
            .rst_i         (rst_pi),
            .codigo_gray_i (codigo_gray_pi),
            .codigo_bin_o  (codigo_bin)
        );

        module_bin_to_bcd # (4) SUBMODULE_BIN_BCD (
            .clk_i (clk_pi),
            .rst_i (rst_pi),
            .bin_i (codigo_bin),
            .bcd_o (codigo_bcd)
        );

        module_7_segments # (DISPLAY_REFRESH) SUBMODULE_DISPLAY (
            .clk_i    (clk_pi),
            .rst_i    (rst_pi),
            .bcd_i    (codigo_bcd),
            .anodo_o  (anodo_po),
            .catodo_o (catodo_po)    
        );
    endgenerate

    assign codigo_bin_led_po = ~codigo_bin; // Asignación directa
    
endmodule

src/sim/module_tb.v
`timescale 1ns/1ns

module test;

    reg clk_i = 0;
    reg rst_i;
    reg [3 : 0] codigo_gray_i;

    wire [1 : 0] anodo_o;
    wire [6 : 0] catodo_o;
    wire [3 : 0] codigo_bin_led_o;

    module_top_deco_gray # (6, 5) DUT 
    (

        .clk_pi            (clk_i),
        .rst_pi            (rst_i),
        .codigo_gray_pi    (codigo_gray_i),
        .anodo_po          (anodo_o),
        .catodo_po         (catodo_o),              
        .codigo_bin_led_po (codigo_bin_led_o)
    );

    always begin
        
        clk_i = ~clk_i;
        #10;
    end
    
    initial begin
        
        rst_i = 0;
        #30;
        rst_i = 1;

        codigo_gray_i = 4'b0000; #100;
        codigo_gray_i = 4'b0001; #100;
        codigo_gray_i = 4'b0011; #100;
        codigo_gray_i = 4'b0010; #100;
        codigo_gray_i = 4'b0110; #100;
        codigo_gray_i = 4'b0111; #100;
        codigo_gray_i = 4'b0101; #100;
        codigo_gray_i = 4'b0100; #100;
        codigo_gray_i = 4'b1100; #100;
        codigo_gray_i = 4'b1101; #100;
        codigo_gray_i = 4'b1111; #100;
        codigo_gray_i = 4'b1110; #100;
        codigo_gray_i = 4'b1010; #100;
        codigo_gray_i = 4'b1011; #100;
        codigo_gray_i = 4'b1001; #100;
        codigo_gray_i = 4'b1000; #100;

        #1000;
        $finish;
    end


    initial begin
        $dumpfile("module_deco_gray.vcd");
        $dumpvars(0, test);
    end

endmodule

src/build/module_deco_gray.vcd
$date
	Sat Aug 24 21:42:50 2024
$end
$version
	Icarus Verilog
$end
$timescale
	1ns
$end
$scope module test $end
$var wire 4 ! codigo_bin_led_o [3:0] $end
$var wire 7 " catodo_o [6:0] $end
$var wire 2 # anodo_o [1:0] $end
$var reg 1 $ clk_i $end
$var reg 4 % codigo_gray_i [3:0] $end
$var reg 1 & rst_i $end
$scope module DUT $end
$var wire 1 $ clk_pi $end
$var wire 4 ' codigo_bin_led_po [3:0] $end
$var wire 4 ( codigo_gray_pi [3:0] $end
$var wire 1 & rst_pi $end
$var wire 4 ) codigo_bin [3:0] $end
$var wire 8 * codigo_bcd [7:0] $end
$var wire 7 + catodo_po [6:0] $end
$var wire 2 , anodo_po [1:0] $end
$var parameter 32 - DISPLAY_REFRESH $end
$var parameter 32 . INPUT_REFRESH $end
$scope module SUBMODULE_BIN_BCD $end
$var wire 1 $ clk_i $end
$var wire 1 & rst_i $end
$var wire 4 / bin_i [3:0] $end
$var parameter 32 0 WIDTH $end
$var reg 8 1 bcd_o [7:0] $end
$var reg 4 2 decenas [3:0] $end
$var reg 4 3 decenas_sync [3:0] $end
$var reg 4 4 unidades [3:0] $end
$var reg 4 5 unidades_sync [3:0] $end
$upscope $end
$scope module SUBMODULE_DISPLAY $end
$var wire 8 6 bcd_i [7:0] $end
$var wire 1 $ clk_i $end
$var wire 1 & rst_i $end
$var parameter 32 7 DISPLAY_REFRESH $end
$var parameter 32 8 WIDTH_DISPLAY_COUNTER $end
$var reg 2 9 anodo_o [1:0] $end
$var reg 7 : catodo_o [6:0] $end
$var reg 3 ; cuenta_salida [2:0] $end
$var reg 2 < decena_unidad [1:0] $end
$var reg 4 = digito_o [3:0] $end
$var reg 1 > en_conmutador $end
$upscope $end
$scope module SUBMODULE_INPUT $end
$var wire 1 $ clk_i $end
$var wire 4 ? codigo_gray_i [3:0] $end
$var wire 1 & rst_i $end
$var parameter 32 @ INPUT_REFRESH $end
$var parameter 32 A WIDTH $end
$var parameter 32 B WIDTH_INPUT_COUNTER $end
$var reg 4 C codigo_bin_o [3:0] $end
$var reg 4 D codigo_gray_sync_r [3:0] $end
$var reg 3 E cuenta_entrada [2:0] $end
$var reg 1 F en_lectura $end
$scope begin $unm_blk_35 $end
$var reg 1 G bit_a $end
$var reg 1 H bit_b $end
$var reg 1 I bit_c $end
$var reg 1 J bit_d $end
$upscope $end
$upscope $end
$upscope $end
$upscope $end
$enddefinitions $end
$comment Show the parameter values. $end
$dumpall
b11 B
b100 A
b110 @
b11 8
b101 7
b100 0
b110 .
b101 -
$end
#0
$dumpvars
0J
0I
0H
0G
0F
b101 E
b0 D
b0 C
bx ?
0>
b0 =
b0 <
b100 ;
b1000000 :
b10 9
b0 6
b0 5
b0 4
b0 3
b0 2
b0 1
b0 /
b10 ,
b1000000 +
b0 *
b0 )
bx (
b1111 '
0&
bx %
1$
b10 #
b1000000 "
b1111 !
$end
#10
0$
#20
1$
#30
0$
b0 %
b0 (
b0 ?
1&
#40
b11 ;
b100 E
1$
#50
0$
#60
b10 ;
b11 E
1$
#70
0$
#80
b1 ;
b10 E
1$
#90
0$
#100
b0 ;
b1 E
1$
#110
0$
#120
1>
b100 ;
b0 E
1$
#130
0$
b1 %
b1 (
b1 ?
#140
b1 #
b1 ,
b1 9
0>
b11 ;
b1 <
1F
b101 E
1$
#150
0$
#160
b1110 !
b1110 '
b1 4
b1 )
b1 /
b1 C
1J
b10 ;
0F
b100 E
b1 D
1$
#170
0$
#180
b1 ;
b1 5
b11 E
1$
#190
0$
#200
b1 *
b1 1
b1 6
b0 ;
b10 E
1$
#210
0$
#220
1>
b100 ;
b1 E
1$
#230
0$
b11 %
b11 (
b11 ?
#240
b11 #
b11 ,
b11 9
0>
b11 ;
b0 E
b10 <
1$
#250
0$
#260
b10 ;
1F
b101 E
1$
#270
0$
#280
b1101 !
b1101 '
b10 4
b10 )
b10 /
b10 C
1I
b1 ;
0F
b100 E
b11 D
1$
#290
0$
#300
b0 ;
b10 5
b11 E
1$
#310
0$
#320
b10 *
b10 1
b10 6
1>
b100 ;
b10 E
1$
#330
0$
b10 %
b10 (
b10 ?
#340
0>
b11 ;
b11 <
b1 E
1$
#350
0$
#360
b10 ;
b0 E
1$
#370
0$
#380
b1 ;
1F
b101 E
1$
#390
0$
#400
b1100 !
b1100 '
b11 4
b11 )
b11 /
b11 C
0J
b0 ;
0F
b100 E
b10 D
1$
#410
0$
#420
1>
b100 ;
b11 5
b11 E
1$
#430
0$
b110 %
b110 (
b110 ?
#440
b110000 "
b110000 +
b110000 :
b11 =
b10 #
b10 ,
b10 9
b11 *
b11 1
b11 6
0>
b11 ;
b10 E
b0 <
1$
#450
0$
#460
b10 ;
b1 E
1$
#470
0$
#480
b1 ;
b0 E
1$
#490
0$
#500
b0 ;
1F
b101 E
1$
#510
0$
#520
b1011 !
b1011 '
b100 4
b100 )
b100 /
b100 C
1H
1>
b100 ;
0F
b100 E
b110 D
1$
#530
0$
b111 %
b111 (
b111 ?
#540
b1000000 "
b1000000 +
b1000000 :
b1 #
b1 ,
b1 9
b0 =
0>
b11 ;
b100 5
b1 <
b11 E
1$
#550
0$
#560
b100 *
b100 1
b100 6
b10 ;
b10 E
1$
#570
0$
#580
b1 ;
b1 E
1$
#590
0$
#600
b0 ;
b0 E
1$
#610
0$
#620
1>
b100 ;
1F
b101 E
1$
#630
0$
b101 %
b101 (
b101 ?
#640
b1001 !
b1001 '
b110 4
b110 )
b110 /
b110 C
1J
0I
b11 #
b11 ,
b11 9
0>
b11 ;
0F
b100 E
b101 D
b10 <
1$
#650
0$
#660
b10 ;
b110 5
b11 E
1$
#670
0$
#680
b110 *
b110 1
b110 6
b1 ;
b10 E
1$
#690
0$
#700
b0 ;
b1 E
1$
#710
0$
#720
1>
b100 ;
b0 E
1$
#730
0$
b100 %
b100 (
b100 ?
#740
0>
b11 ;
b11 <
1F
b101 E
1$
#750
0$
#760
b1000 !
b1000 '
b111 4
b111 )
b111 /
b111 C
0J
b10 ;
0F
b100 E
b100 D
1$
#770
0$
#780
b1 ;
b111 5
b11 E
1$
#790
0$
#800
b111 *
b111 1
b111 6
b0 ;
b10 E
1$
#810
0$
#820
1>
b100 ;
b1 E
1$
#830
0$
b1100 %
b1100 (
b1100 ?
#840
b1111000 "
b1111000 +
b1111000 :
b111 =
b10 #
b10 ,
b10 9
0>
b11 ;
b0 E
b0 <
1$
#850
0$
#860
b10 ;
1F
b101 E
1$
#870
0$
#880
b111 !
b111 '
b1000 4
b1000 )
b1000 /
b1000 C
1G
b1 ;
0F
b100 E
b1100 D
1$
#890
0$
#900
b0 ;
b1000 5
b11 E
1$
#910
0$
#920
b1000 *
b1000 1
b1000 6
1>
b100 ;
b10 E
1$
#930
0$
b1101 %
b1101 (
b1101 ?
#940
b1000000 "
b1000000 +
b1000000 :
b1 #
b1 ,
b1 9
b0 =
0>
b11 ;
b1 <
b1 E
1$
#950
0$
#960
b10 ;
b0 E
1$
#970
0$
#980
b1 ;
1F
b101 E
1$
#990
0$
#1000
b110 !
b110 '
b1001 4
b1001 )
b1001 /
b1001 C
1J
b0 ;
0F
b100 E
b1101 D
1$
#1010
0$
#1020
1>
b100 ;
b1001 5
b11 E
1$
#1030
0$
b1111 %
b1111 (
b1111 ?
#1040
b11 #
b11 ,
b11 9
b1001 *
b1001 1
b1001 6
0>
b11 ;
b10 E
b10 <
1$
#1050
0$
#1060
b10 ;
b1 E
1$
#1070
0$
#1080
b1 ;
b0 E
1$
#1090
0$
#1100
b0 ;
1F
b101 E
1$
#1110
0$
#1120
b101 !
b101 '
b1 2
b0 4
b1010 )
b1010 /
b1010 C
1I
1>
b100 ;
0F
b100 E
b1111 D
1$
#1130
0$
b1110 %
b1110 (
b1110 ?
#1140
0>
b11 ;
b1 3
b0 5
b11 <
b11 E
1$
#1150
0$
#1160
b10000 *
b10000 1
b10000 6
b10 ;
b10 E
1$
#1170
0$
#1180
b1 ;
b1 E
1$
#1190
0$
#1200
b0 ;
b0 E
1$
#1210
0$
#1220
1>
b100 ;
1F
b101 E
1$
#1230
0$
b1010 %
b1010 (
b1010 ?
#1240
b11 !
b11 '
b10 4
b1 2
b1100 )
b1100 /
b1100 C
0J
0H
b10 #
b10 ,
b10 9
0>
b11 ;
0F
b100 E
b1010 D
b0 <
1$
#1250
0$
#1260
b10 ;
b10 5
b11 E
1$
#1270
0$
#1280
b10010 *
b10010 1
b10010 6
b1 ;
b10 E
1$
#1290
0$
#1300
b0 ;
b1 E
1$
#1310
0$
#1320
1>
b100 ;
b0 E
1$
#1330
0$
b1011 %
b1011 (
b1011 ?
#1340
b1111001 "
b1111001 +
b1111001 :
b1 =
b1 #
b1 ,
b1 9
0>
b11 ;
b1 <
1F
b101 E
1$
#1350
0$
#1360
b10 !
b10 '
b1 2
b11 4
b1101 )
b1101 /
b1101 C
1J
b10 ;
0F
b100 E
b1011 D
1$
#1370
0$
#1380
b1 ;
b11 5
b11 E
1$
#1390
0$
#1400
b10011 *
b10011 1
b10011 6
b0 ;
b10 E
1$
#1410
0$
#1420
1>
b100 ;
b1 E
1$
#1430
0$
b1001 %
b1001 (
b1001 ?
#1440
b1000000 "
b1000000 +
b1000000 :
b11 #
b11 ,
b11 9
b0 =
0>
b11 ;
b0 E
b10 <
1$
#1450
0$
#1460
b10 ;
1F
b101 E
1$
#1470
0$
#1480
b1 !
b1 '
b1 2
b100 4
b1110 )
b1110 /
b1110 C
0I
b1 ;
0F
b100 E
b1001 D
1$
#1490
0$
#1500
b0 ;
b100 5
b11 E
1$
#1510
0$
#1520
b10100 *
b10100 1
b10100 6
1>
b100 ;
b10 E
1$
#1530
0$
b1000 %
b1000 (
b1000 ?
#1540
0>
b11 ;
b11 <
b1 E
1$
#1550
0$
#1560
b10 ;
b0 E
1$
#1570
0$
#1580
b1 ;
1F
b101 E
1$
#1590
0$
#1600
b0 !
b0 '
b1 2
b101 4
b1111 )
b1111 /
b1111 C
0J
b0 ;
0F
b100 E
b1000 D
1$
#1610
0$
#1620
1>
b100 ;
b101 5
b11 E
1$
#1630
0$
#1640
b10010 "
b10010 +
b10010 :
b101 =
b10 #
b10 ,
b10 9
b10101 *
b10101 1
b10101 6
0>
b11 ;
b10 E
b0 <
1$
#1650
0$
#1660
b10 ;
b1 E
1$
#1670
0$
#1680
b1 ;
b0 E
1$
#1690
0$
#1700
b0 ;
1F
b101 E
1$
#1710
0$
#1720
1>
b100 ;
0F
b100 E
1$
#1730
0$
#1740
b1111001 "
b1111001 +
b1111001 :
b1 #
b1 ,
b1 9
b1 =
0>
b11 ;
b1 <
b11 E
1$
#1750
0$
#1760
b10 ;
b10 E
1$
#1770
0$
#1780
b1 ;
b1 E
1$
#1790
0$
#1800
b0 ;
b0 E
1$
#1810
0$
#1820
1>
b100 ;
1F
b101 E
1$
#1830
0$
#1840
b1000000 "
b1000000 +
b1000000 :
b11 #
b11 ,
b11 9
b0 =
0>
b11 ;
0F
b100 E
b10 <
1$
#1850
0$
#1860
b10 ;
b11 E
1$
#1870
0$
#1880
b1 ;
b10 E
1$
#1890
0$
#1900
b0 ;
b1 E
1$
#1910
0$
#1920
1>
b100 ;
b0 E
1$
#1930
0$
#1940
0>
b11 ;
b11 <
1F
b101 E
1$
#1950
0$
#1960
b10 ;
0F
b100 E
1$
#1970
0$
#1980
b1 ;
b11 E
1$
#1990
0$
#2000
b0 ;
b10 E
1$
#2010
0$
#2020
1>
b100 ;
b1 E
1$
#2030
0$
#2040
b10010 "
b10010 +
b10010 :
b101 =
b10 #
b10 ,
b10 9
0>
b11 ;
b0 E
b0 <
1$
#2050
0$
#2060
b10 ;
1F
b101 E
1$
#2070
0$
#2080
b1 ;
0F
b100 E
1$
#2090
0$
#2100
b0 ;
b11 E
1$
#2110
0$
#2120
1>
b100 ;
b10 E
1$
#2130
0$
#2140
b1111001 "
b1111001 +
b1111001 :
b1 #
b1 ,
b1 9
b1 =
0>
b11 ;
b1 <
b1 E
1$
#2150
0$
#2160
b10 ;
b0 E
1$
#2170
0$
#2180
b1 ;
1F
b101 E
1$
#2190
0$
#2200
b0 ;
0F
b100 E
1$
#2210
0$
#2220
1>
b100 ;
b11 E
1$
#2230
0$
#2240
b1000000 "
b1000000 +
b1000000 :
b11 #
b11 ,
b11 9
b0 =
0>
b11 ;
b10 E
b10 <
1$
#2250
0$
#2260
b10 ;
b1 E
1$
#2270
0$
#2280
b1 ;
b0 E
1$
#2290
0$
#2300
b0 ;
1F
b101 E
1$
#2310
0$
#2320
1>
b100 ;
0F
b100 E
1$
#2330
0$
#2340
0>
b11 ;
b11 <
b11 E
1$
#2350
0$
#2360
b10 ;
b10 E
1$
#2370
0$
#2380
b1 ;
b1 E
1$
#2390
0$
#2400
b0 ;
b0 E
1$
#2410
0$
#2420
1>
b100 ;
1F
b101 E
1$
#2430
0$
#2440
b10010 "
b10010 +
b10010 :
b101 =
b10 #
b10 ,
b10 9
0>
b11 ;
0F
b100 E
b0 <
1$
#2450
0$
#2460
b10 ;
b11 E
1$
#2470
0$
#2480
b1 ;
b10 E
1$
#2490
0$
#2500
b0 ;
b1 E
1$
#2510
0$
#2520
1>
b100 ;
b0 E
1$
#2530
0$
#2540
b1111001 "
b1111001 +
b1111001 :
b1 #
b1 ,
b1 9
b1 =
0>
b11 ;
b1 <
1F
b101 E
1$
#2550
0$
#2560
b10 ;
0F
b100 E
1$
#2570
0$
#2580
b1 ;
b11 E
1$
#2590
0$
#2600
b0 ;
b10 E
1$
#2610
0$
#2620
1>
b100 ;
b1 E
1$
